<BackupInst xmlns="http://www.microsoft.com/GroupPolicy/GPOOperations/Manifest"><GPOGuid><![CDATA[{4CE82977-C5D6-4443-8717-C2956471A1CF}]]></GPOGuid><GPODomain><![CDATA[sos.lan]]></GPODomain><GPODomainGuid><![CDATA[{0069038d-2ece-441b-81b7-6f6254c1b9b8}]]></GPODomainGuid><GPODomainController><![CDATA[SOSDC1.sos.lan]]></GPODomainController><BackupTime><![CDATA[2020-08-18T03:36:48]]></BackupTime><ID><![CDATA[{EA6A9934-8B4A-4666-A648-D9872DE2164C}]]></ID><Comment><![CDATA[]]></Comment><GPODisplayName><![CDATA[DoD - Outlook 2013]]></GPODisplayName></BackupInst>
