<Backups xmlns="http://www.microsoft.com/GroupPolicy/GPOOperations/Manifest" xmlns:mfst="http://www.microsoft.com/GroupPolicy/GPOOperations/Manifest" mfst:version="1.0"><BackupInst><GPOGuid><![CDATA[{677B684C-DCE0-4DD4-B4D9-FC5531ED6000}]]></GPOGuid><GPODomain><![CDATA[sos.lan]]></GPODomain><GPODomainGuid><![CDATA[{0069038d-2ece-441b-81b7-6f6254c1b9b8}]]></GPODomainGuid><GPODomainController><![CDATA[SOSDC1.sos.lan]]></GPODomainController><BackupTime><![CDATA[2020-08-27T22:08:29]]></BackupTime><ID><![CDATA[{1452F2F1-4B58-4A46-8F79-E915799E657E}]]></ID><Comment><![CDATA[]]></Comment><GPODisplayName><![CDATA[DoD - OneDrive for Business 2016 - User]]></GPODisplayName></BackupInst></Backups>