<Backups xmlns="http://www.microsoft.com/GroupPolicy/GPOOperations/Manifest" xmlns:mfst="http://www.microsoft.com/GroupPolicy/GPOOperations/Manifest" mfst:version="1.0"><BackupInst><GPOGuid><![CDATA[{16C99212-C401-4F17-863C-0D29DC1E5BB7}]]></GPOGuid><GPODomain><![CDATA[SIM.LAN]]></GPODomain><GPODomainGuid><![CDATA[{e9726a3d-a871-48bb-8946-f04e3b9c84e9}]]></GPODomainGuid><GPODomainController><![CDATA[SIMDC2.SIM.LAN]]></GPODomainController><BackupTime><![CDATA[2020-07-22T00:48:18]]></BackupTime><ID><![CDATA[{5C4F0C27-5CD7-4BB5-BC95-52985F549CA0}]]></ID><Comment><![CDATA[]]></Comment><GPODisplayName><![CDATA[DoD PowerPoint 2013]]></GPODisplayName></BackupInst></Backups>